photosynthesis_metrics/__init__.py
photosynthesis_metrics/base.py
photosynthesis_metrics/brisque.py
photosynthesis_metrics/fid.py
photosynthesis_metrics/gmsd.py
photosynthesis_metrics/gs.py
photosynthesis_metrics/isc.py
photosynthesis_metrics/kid.py
photosynthesis_metrics/msid.py
photosynthesis_metrics/ssim.py
photosynthesis_metrics/tv.py
photosynthesis_metrics/utils.py
photosynthesis_metrics/vif.py
photosynthesis_metrics/feature_extractors/__init__.py
photosynthesis_metrics/feature_extractors/fid_inception.py
tests/__init__.py
tests/test_brisque.py
tests/test_fid.py
tests/test_gmsd.py
tests/test_gs.py
tests/test_is.py
tests/test_kid.py
tests/test_msid.py
tests/test_ssim.py
tests/test_tv.py
tests/test_utils.py
tests/test_vif.py
photosynthesis_metrics-0.4.0.dist-info/LICENSE
photosynthesis_metrics-0.4.0.dist-info/METADATA
photosynthesis_metrics-0.4.0.dist-info/WHEEL
photosynthesis_metrics-0.4.0.dist-info/top_level.txt
photosynthesis_metrics-0.4.0.dist-info/RECORD
