Metadata-Version: 2.1
Name: photosynthesis-metrics
Version: 0.4.0
Summary: Measures and metrics for image2image tasks. PyTorch.
Home-page: https://github.com/photosynthesis-team/photosynthesis.metrics
Author: Sergey Kastryulin
Author-email: snk4tr@gmail.com
License: UNKNOWN
Platform: UNKNOWN
Classifier: Programming Language :: Python :: 3
Classifier: License :: OSI Approved :: Apache Software License
Classifier: Operating System :: OS Independent
Requires-Dist: torch (!=1.5.0,>=1.2.0)
Requires-Dist: scipy (==1.3.3)
Requires-Dist: torchvision (!=0.6.0,>=0.4.0)
